sco_client-0.5.0.dist-info/DESCRIPTION.rst
sco_client-0.5.0.dist-info/METADATA
sco_client-0.5.0.dist-info/RECORD
sco_client-0.5.0.dist-info/WHEEL
sco_client-0.5.0.dist-info/metadata.json
sco_client-0.5.0.dist-info/top_level.txt
scocli/__init__.py
scocli/__main__.py
scocli/cli.py
scocli/experiment.py
scocli/funcdata.py
scocli/image.py
scocli/model.py
scocli/modelrun.py
scocli/scoserv.py
scocli/subject.py
