Metadata-Version: 2.0
Name: sco-client
Version: 0.5.0
Summary: Library to interact with Standard Cortical Observer Web API
Home-page: https://github.com/heikomuller/sco-client
Author: Heiko Mueller
Author-email: heiko.muller@gmail.com
License: GPLv3
Keywords: neuroscience vision cortex
Platform: UNKNOWN
Requires-Dist: python-dateutil
Requires-Dist: requests
Requires-Dist: sco-datastore
Requires-Dist: sco-engine
